{
    "text": "Продается прибыльное кафе в торгово-развлекательном комплексе «Афимолл Сити», расположенное на первом этаже , в месте с большим трафиком. Арендуемое помещение 38 кв.м , ставка 800 000 р, включая коммунальные платежи, заключен долгосрочный договор аренды до 2021 года. Производимая продукция: кондитерские изделия, французская выпечка, суши-сеты, бизес ланчи, завтраки, обеды и кофе. Оборудовано 18 посадочных мест, кухня полного цикла, все торговое и холодильное оборудование находится в собственности. Ведется активная рекламная компания в соц сетях, среди сотрудников ТЦ и ближайших БЦ. Установлена программа учета «iiko». В штате работает 10 человек: 3 повара,4 бариста, управляющий и 2 кассира ФОТ 500 000 р. Среднемесячные обороты 4 000 000 р, прибыль 600 000 р. Стоимость бизнеса 9 000 000р.",
    "price": "9000000",
    "address": "Москва",
    "header": "Кафе в Афимолл Сити, прибыль 600 000р",
    "contact": "Владимир",
    "id": "1019964058",
    "date": "7 октября"
}