{
    "text": "Продам работающий бизнес ,продуктовый отдел в магазине Русь цокольный этаж.Цена включает в себя оборудование стоимостью ориентировочно 160 000 (витрина морозильная ,2 витрины охлажденные ,видеонаблюдение ,кондиционер,муз.центр,шкаф универсальный, шкаф охлажденный, ларь морозильный,шкаф охлажд. под напитки со стеклянной дверью,весы, инвентарь ,стеллажи.), товарный остаток,базу поставщиков. Либо за 500 000 руб отдел в магазине Русь + торговая точка в павильоне на ул.Октябрьская. Подробности только при личной встрече.",
    "price": "270000",
    "address": "Озерск",
    "header": "Продуктовый отдел (работающий бизнес)",
    "contact": null,
    "id": "1020413653",
    "date": "8 октября"
}