{
    "text": "продам  продуктовый магазин срочно в связи с переездом - продам вместе с товаром и оборудованием - система видео наблюдения - кондиционер - витрины холодильники лари - тепловая завеса - цена указана за всё! Возможна продажа пустого помещения!!! Под магазин - офис - парикмахерскую! Усолье Сибирское Розы Люксембург 9 !",
    "price": "2800000",
    "address": "Усолье-Сибирское",
    "header": "Торговое помещение, 49 м²",
    "contact": null,
    "id": "1032771880",
    "date": null
}