{
    "text": "Продается производство бумажных пакетов в городе Клин. В собственности отдельно-стоящее здание площадью 350 кв. м. и земля 13 соток . Проведены все коммуникации - свет ,вода собственные колодцы, выделенная мощность 100 кВт. В штате 8 человек - все местные жители с зарплатным фондом 240000 р в месяц . Бизнес работает 3 года ,есть своя база постоянных клиентов. Заключены необходимые договора с поставщиками, есть возможность увеличения производственных мощностей. Производство оборудовано всем необходимым - список по запросу. Есть действующий качественный сайт .Среднемесячный оборот 3 000 000 р , прибыль 1 000 000 р. Стоимость бизнеса и имущественного комплекса 17 000 000 р.",
    "price": "17000000",
    "address": "Москва",
    "header": "Пр-во бумажных пакетов,недвижимость в собственност",
    "contact": "Владимир",
    "id": "1089073402",
    "date": "7 октября"
}