{
    "text": "Продаю но не избавляюсь действующий с декабря 2014 года караоке клуб с кафе и магазином в одном кирпичном здании в собственности земли 15 соток по фасаду 38 метров на 30 машина мест газ, свет (100кв), вода  отделка здания Дагестанским камнем, натуральная тротуарная плитка Евро ремонт тёплый пол Немецкая система отопления \"Будерос\" системы вентиляции зима-лето, кондиционирование вай-фай тревожная кнопка видео наблюдение  Три изолированных зала  в Славянске-на-Кубани Краснодарского края ул. Маевское шоссе 1.",
    "price": "20000000",
    "address": "Краснодар",
    "header": "Торговое помещение, 470 м²",
    "contact": "ООО",
    "id": "1095156644",
    "date": null
}