{
    "text": "Отличный прибыльный готовый бизнес Магазин Цифровой и Компьютерной техники магазин работает 2 года. Магазин в арендованном помещении стоимость аренды низкая и расти не собирается. Занимаемся продажей: Смартфонов, Акссесуары, Ноутбуки, Видеорегистраторами, Пультами управления. Все не перечислеть лучше лично при встречи. Можно так же расширить ассортимент товаров еще есть куда расти. Магазин расположен в хорошем месте рядом с автобусной остановкой и в 300 метрах находиться остановка электрички от туда так же идут люди. Так же оказываем услуги по ремонту техники, ноутбуки, компьютеры, смартфоны. Идеально для мастера по телефоном так как в день поступает от 1 до 10 аппаратов. В стоимость входит все оборудование, Укомплектованное рабочие место, программа ведения учёта, Витрины, товарный остаток. Так же передадим всех поставщиков товара, обучим и поможем навичку. Одним словом все под ключ.",
    "price": "650000",
    "address": "Краснодар",
    "header": "Магазин Цифровой и Компьютерной техники + Ремонт",
    "contact": null,
    "id": "1114461867",
    "date": null
}