{
    "text": "Продам готовый бизнес ОГРОМНЫЙ ПЛЮС - НЕТ АРЕНДНОЙ ПЛАТЫ, ТОЛЬКО КОММУНАЛКА. в оборудование и рекламу вложено порядка 300 тысяч. Сделана профессиональная фото сессия блюд (уникальные фото для сайта и меню и буклетов стоимостью порядка 20 тысяч.\\ Сайт с онлайн заказом и оплатой. Действующая кухня в кафе (работает как на зал, так и на доставку). На Зал работает 4й месяц, на доставку только начали Есть все оборудование для производства пиццы и роллов. Нужно только заниматься. Продаю ввиду финансовых затруднений. Торг и рассрочка рассматриваются.",
    "price": "320000",
    "address": "Нижний Новгород",
    "header": "Кухня в кафе + доставка",
    "contact": "роман",
    "id": "1131170903",
    "date": "8 октября"
}