{
    "text": "Продам законсервированная после реконструкции АЗС,операторская 24м.кв.(2комнаты)4млн.руб. При АЗС двухэтажное административно-техническое здание, 24*12, находится в черте города, твердое покрытие, от центра 5 мин.езды. В здании находится авто мойка, авто мастерская, бытовые помещения, шино-монташ, вода, газ,канализация электроэнергия, видео наблюдение, телефон, интернет, 6млн.руб",
    "price": "10000000",
    "address": "Алексеевка",
    "header": "Продается АЗС с админ.техническим зданием",
    "contact": null,
    "id": "1134799957",
    "date": null
}