{
    "text": "Розничная торговля часами и аксессуарами к ним, мужской, женский, детский ассортимент. Бизнесу 6 лет, торговая точка расположена в торговом центре в центре города, рядом с крупным федеральным арендатором, выгодные условия аренды, очень большой товарный остаток, доход стабильный, торговое оборудование из ламината с диодной подсветкой, специальное оборудование для торговли часами, яркий световой короб, остаётся персонал (очень выгодные условия для работодателя), всё расскажу о поставщиках и дальнейшем ведении бизнеса. Продаю неспешно. т.452 восемьсот восемьдесят восемь, это действительно выгодное предложение в канун НГ!!!",
    "price": "149000",
    "address": "Киров",
    "header": "Отдел часов",
    "contact": "Анна",
    "id": "1145416153",
    "date": "4 октября"
}