{
    "text": "Продам кофейню формата «кофе с собой». Передам все товарные остатки, рецептуры, поставщиков. Хорошие товарные остатки. Из оборудования в собственности холодильник, морозильник, аппарат для хот дога, блендер. Кофемашина и кофемолка в аренде. На летний сезон + уличная продажа мороженого. Хорошие условия по договору аренды места. В высокий сезон очень хороший пешеходный трафик. Ленина 132 Возможна рассрочка платежа",
    "price": "350000",
    "address": "Сочи",
    "header": "Кофейня Кофе с собой",
    "contact": "Екатерина",
    "id": "1213735006",
    "date": null
}