{
    "text": "Сдается кабинет под любые виды деятельности: косметология, массаж, депиляция, маникюр/педикюр, наращивание ресниц, обучающие курсы и т.п. мастерам со своей клиентской базой. Кабинет 15 кв.м. с окном, кондиционером и мокрой точкой (гор/хол вода). На полный месяц. Возможно присоединения еще одной комнаты 10кв.м. В стоимость входят коммунальные услуги, уборка, встреча ваших гостей администратором.",
    "price": "35000",
    "address": "Москва",
    "header": "Сдается кабинет косметолога в салоне красоты",
    "contact": "Ирина",
    "id": "1222809838",
    "date": null
}