{
    "text": "Питомник с дикорастущими плодово-ягодными культурами. (Голубика, брусника, клюква, княженика) Существует 7 лет, есть ООО со всеми необходимыми сферами деятельности. Штат 5 человек. Продам целиком (как бизнес), либо только саженцы.Находится в 25 км от г. Киров. Продается в связи с закрытием данного направления. Оптовая оценка саженцев 5 млн рублей. Целиком продам за 1,5 млн.Возможен торг. Список: Голубика\tУзколистная, форма 07\t6 летние растения\t445 шт\tОтдельные растения Узколистная, форма 07\t4 летние растения\t20 шт\tОтдельные растения Узколистная, форма 07\t2-3 летние растения\t145 шт\tОтдельные растения Клюква\tБен-лир\tМноголетнее растение\t1200 м2 (20000 шт)\tРастет сплошным ковром 23/3\tМноголетнее растение\t350 м2 (6000 шт)\tРастет сплошным ковром Дар Костромы\tМноголетнее растение\t8 м2 (150 шт)\tРастет сплошным ковром Соминская\tМноголетнее растение\t1 м2 (20 шт)\tРастет сплошным ковром Северянка\tМноголетнее растение\t1 м2 (20 шт)\tРастет сплошным ковром Алая заповедная\tМноголетнее растение\t1 м2 (20 шт)\tРастет сплошным ковром Хотавецкая\tМноголетнее растение\t1 м2 (20 шт)\tРастет сплошным ковром Краса Севера\tМноголетнее растение\t1 м2 (20 шт)\tРастет сплошным ковром Вируссааре\tМноголетнее растение\t1 м2 (20 шт)\tРастет сплошным ковром Тарту\tМноголетнее растение\t1 м2 (20 шт)\tРастет сплошным ковром Княженика\tАстра\tМноголетнее растение\t60 м2 (примерно 10 000 шт)\tРастет сплошным ковром София\tМноголетнее растение\t60 м2 (примерно 10000 шт)\tРастет сплошным ковром Беата\tМноголетнее растение\t20 м2 (примерно 3000 шт)\tРастет сплошным ковром Астра\tМноголетнее растение\t10 м2 (примерно 1500 шт)\tРастет сплошным ковром Брусника\tКостромичка розовая\t2-3 летние растения\t187 шт\tОтдельные растения",
    "price": "1500000",
    "address": "Киров",
    "header": "Продажа питомника с плодово-ягодными культурами",
    "contact": null,
    "id": "1229213678",
    "date": "8 октября"
}