{
    "text": "Продаю современную ферму по выращиванию шампиньонов производительностью 5600 тонн/год. 28 камер по 723 м. Построено и работает 6 камер. Голандская технология, новое оборудование. В данный момент выращиваем 95 тонн шампиньонов в месяц, окупаемость 6, 2 лет. При инвестировании в проект окупаемость снижается до 4,2  лет. Персонал 50 человек. Помощь в получении кредита под покупку данного объекта.",
    "price": "160000000",
    "address": "Ростов-на-Дону",
    "header": "Продаю ферму по выращиванию шампиньонов",
    "contact": null,
    "id": "1238000800",
    "date": "4 октября"
}