{
    "text": "НАЧАЛСЯ СЕЗОН МЯСА!!!!!!!!!!!!!!!!! Продаем готовый бизнес ( мясной магазин) со всем новым оборудованием (((((((4 витрины холодильные, 1 бонета минус 20С,2-е весов штрих-принт, компьютер товароведа, компьютер кассира, 1С Профи, касса Штрих-М, экваринг, камера холодильная, агрегат холодильный Полаир, столы нержавейка 9шт, мясорубка Торг Марш, горячий стол упаковочный, шприц колбасный, 2 кондиционера на 70кв м и на 21 кв м, тележки траспартерные, бойлер электрический 80л. И т.д.)))))))))в центре города. Кооперативный рынок. Выручку, доход- все расскажем при встрече.  Продаем, так как нет времени заниматься магазином.Звоните. Реальному покупателю немного уступим.",
    "price": "700008",
    "address": "Краснодар",
    "header": "Магазин по продаже мяса",
    "contact": null,
    "id": "1265441792",
    "date": "9 октября"
}