{
    "text": "В стоимость входит: -Кофемобиль (citroen 2010г. Со всем оборудованием и сертифицированным газовым оборудованием для кофемашины) -Кофемашина (sanmarco две группы) -Кофемолка -Все необходимое оборудование для приготовления напитков, товарный остаток А так же все необходимые договоренности с арендадателями, арендованный (отапливаемый гараж),  место у входа в парк, возможность встать у м.Войковская и на ее территории. Точка работает практически каждый день, бариста готов остаться работать или обучить ваш персонал. Прибыль точки в не сезон 35-40т.р. с учетом того, что работает сотрудник. Так же расскажу все нюансы направления, объясню причину продажи и поделюсь опытом, если вы реально заинтересованы в покупке. Звонить с 9:00 до 20:00",
    "price": "560000",
    "address": "Москва",
    "header": "Продам приносящий прибыль кофемобиль",
    "contact": null,
    "id": "1270590529",
    "date": null
}