{
    "text": "Продаю действующий магазин.Овощи, фрукты,специи,соленья, восточные сладости, соки, продукты здорового питания и многое другое .Магазин с большим, ассортиментом, бегущая строка,холодильник, реклама с подсветкой, кролик (привлечение клиентов).Пожарная сигнализация, охрана. Наработанная клиентская база, большой пеший и автомобильный трафик.Помещение в аренде 38кв.м. Аренда оплачена на месяц вперед.Срочная продажа!!!Рассмотрю обмен на авто. Все прозрачно.Остальные вопросы по телефону.Торг уместен.!",
    "price": "300000",
    "address": "Краснодар",
    "header": "Фреш Маркет",
    "contact": null,
    "id": "1277617911",
    "date": "5 октября"
}