{
    "text": "Продаётся действующий бизнес «КОФЕ С СОБОЙ». Утеплённый киоск с оборудованием для приготовления кофейных напитков: кофемашина, кофемолка, водонагреватель, холодильник. Расположен в центре п. Тульского, возле универмага (земля в аренде, аренда символическая). Более подробная информация по телефону. Рассмотрим продажу киоска без оборудования, с вывозом его для других целей.",
    "price": "120000",
    "address": "Тульский",
    "header": "Готовый бизнес «кофе С собой»",
    "contact": null,
    "id": "1280213475",
    "date": null
}