{
    "text": "Продаётся действующий бизнес. Автотранспортное предприятие. Существует с 2004 года. Офисно-производственное здание 215,2 кв.м.в собственности. Земля 0,606 Га. Низкий ежегодный имущественный налог. Сертифицированный автосервис на 4е поста. Два гидравлических подъемника, два механических подъемника. В собственности 30 легковых автомобилей с лицензиями на пассажирские перевозки. Действующее ООО с отличной кредитной историей",
    "price": "15000000",
    "address": "Барнаул",
    "header": "Действующий бизнес",
    "contact": null,
    "id": "1299142919",
    "date": "9 октября"
}