{
    "text": "Аренда силосов в Свердловской области от собственника!!! В посёлке Кедровка (30 км от Екатеринбурга по Режевскому тракту) сдаются в аренду силоса под пищевые сыпучие продукты: Наши преимущества для Вас: 1.\t12 силосов, объём каждого силоса 1.000 тонн. Сдаются как все вместе, так и по отдельности. Можно по тоннажу. 2.\tСилоса немецкого производства и в хорошем состоянии. 3.\tЖ/д подъездные пути, лебёдка для вагонов. 4.\tВозможность разгружать и загружать продукцию грузовым транспортом и ж/д транспортом. 5.\tРаботающие автомобильные весы. 6.\tПри аренде 6-ти силосов и более – Вы дополнительно получаете кабинет – 12 кв метров в Административно-бытовом корпусе. В качестве офисного помещения. 7.\tОхраняемая территория. Есть электричество. 8.\tВозможность арендовать производственные и складские площади (стоимость оговаривается отдельно). 9.\t15 минут до объездной дороги ЕКАД. Стоимость аренды  60.000 рублей за 1 емкость, стоимость зависит от кол-ва арендуемых ёмкостей, срока, условий оплаты, аренды дополнительных объектов. Фотографии прилагаются. Адрес расположения силосов: Свердловская область,  Режевской тракт, поселок Кедровка, ул. Пушкина 55, бывший Кедровский крупяной завод. Звоните, готовы обсуждать любые предложения!",
    "price": "60000",
    "address": "Березовский",
    "header": "Аренда силосов от собственника",
    "contact": null,
    "id": "1323899243",
    "date": null
}