{
    "text": "Ооо С Допуском Сро Продается Ооо С Допуском Сро 1-ого уровня - стройка до 60 млн (возможно повышение) Готовая Строительная Фирма ООО с СРО ООО \"Строй - Инвест\", ИНН по запросу Допуск СРО строителей до 60 млн. (1-й уровень ответственности) + 2 специалиста НРС + оплаченный членский взнос на 6 мес. вперед; ●Р/с в Сбербанке; ●Нулевой оборот; ●Отсутствие задолженностей; ●Положительная история; ●Гарантия юридической чистоты; ●Полный пакет документов; Быстрое переоформление! Смена учредителя и директора от 3-х дней! Так же помогаем в получении допуска СРО! Сделаем допуск по самой низкой цене за 1 день! Под ключ! Предоставим специалистов! Звоните! И мы вас проконсультируем",
    "price": "260000",
    "address": "Москва",
    "header": "Ооо С Допуском Сро",
    "contact": "Константин",
    "id": "1340907087",
    "date": "9 октября"
}