{
    "text": "СОБСТВЕННИК! Эксклюзивный вариант для предпринимателей! Готовый бизнес под ключ! Продажа в связи с переездом в другой город. Продам действующую студию красоты в г. Ростове-на-Дону. Свои клиенты, хорошая проходимость, спальный район (Рядом торговый комплекс МЕРКУРИЙ, МАЯК, Ситилинк). дополнительных вложений не требует. Студия оборудована всем необходимым для работы: техника, мебель, кушетки, кресла, стулья ,столы , и т.д. Есть возможность поставить дополнительно солярий! Сделан качественный дизайнерский ремонт: проводка, разноуровневое освещение, интернет, Wi-fi, телевидение, мебель на заказ, зеркала-багеты. В студии 3 отдельных рабочих помещения + 1 подсобное+ 1 техническое (сан узел с возможностью поставить душ, при необходимости) + коридор ( с возможностью сделать еще одно подсобное помещение для инвентаря): - Маникюрный зал (18 кв.м.) - Парикмахерский зал (18 кв.м.) - Отдельный косметологический кабинет с возможностью поставить солярий! (10 кв.м.) - техническое (сан узел с возможностью поставить душ, при необходимости) + коридор ( с возможностью сделать еще одно подсобное помещение для инвентаря) (15 кв.м.) Возможность сдавать в аренду до 8 рабочих мест! Новый спальный район. Сдано 4 дома (2000 чел.) Рядом жилые районы. В ближайший год год планируется сдача еще 2-х домов. В перспективе до 20 домов + садик + школа! Развитая инфраструктура.Закрытая территория! В данном районе студия такого уровня одна! Дополнительные фото видео высылаю в воцап. Торг уместен.",
    "price": "2990000",
    "address": "Ростов-на-Дону",
    "header": "Салон Красоты. Готовый бизнес",
    "contact": null,
    "id": "1343234465",
    "date": "8 октября"
}