{
    "text": "Продаётся готовый бизнес по продаже снаряжения и оборудованию для высотников и промышленных альпинистов. Передаётся готовый сайт, номер телефона на который поступают звонки, контакты поставщиков, офис если нужен то подберем с низкой арендной ставкой в любом районе города. Всему обучу и расскажу как наладить хорошую прибыль. Возможен вариант сотрудничества по принципу продажи франшизы. Снимаем офис под магазин и начинаем совместные продажи. Делим выручку пополам. Возможны и другие варианты бизнес отношений в этой и других отраслях.",
    "price": "149000",
    "address": "Санкт-Петербург",
    "header": "Бизнес по продаже снаряжения для высоты",
    "contact": "Вадим",
    "id": "1409855300",
    "date": "9 октября"
}