{
    "text": "Готовый Бизнес более 5 лет. Большой потенциал Легко управлять Причина продажи: Смена сферы деятельности. Продается небольшой, легкий в управлении магазин-бар разливного пива в городе Москва. Отличный вариант для желающих начать бизнес. Создавался для себя. Магазин находится в густонаселенном  спальном районе. Большое количество многоэтажных домов. Рядом с магазином есть удобная парковка. Имеется отдельный вход, яркая и заметная рекламная вывеска. Полностью оборудованное помещение. В магазине представлены качественные сорта от российских и зарубежных производителей. Очень много положительных отзывов от благодарных клиентов. Люди приходят от конкурентов и остаются у нас, потому что ведется постоянная работа  над ассортиментом напитков и подобраны те сорта, которые пользуются наибольшим спросом. Имеется страница в Инстаграмм. Клиентов с каждым днем становится все больше. Также можно организовать доставку и расширить ассортимент. Это еще тысяч 500 000 к выручке. Потенциал по выручке у данного места до 1 000 000 руб. и выше. Можно добавить к ассортименту табак и вейпы – в этом районе это пользуется спросом. Помещение 15 м кв. – в аренде.  Есть санузел. Адекватный и приятный собственник помещения. Всё оборудование в собственности. Имеется холодильный агрегат. Температурный режим +5, что позволяет сохранять пиво свежим долгое время. Также в собственности 5 двойных кранов на 8 сортов пива (win tap) хром. 4 крана тип Pegas однопоточных. И Есть возможность подключения дополнительных кранов. Холодильник для напитков в собственности. Витрина для рыбы 0 - +5 в собственности. Налажена система учета. Соседи Мясо и секондхенд.",
    "price": "600000",
    "address": "Москва",
    "header": "Разливное пиво",
    "contact": null,
    "id": "1440891429",
    "date": null
}