{
    "text": "Выставлен на продажу  банный комплекс \"Водопад\" расположенный в 26 комплексе на Московском проспекте. Данный комплекс состоит из  двух просторных саун,  два бассейна с водопадом, комнатами отдыха, рабочее место администратора, продается со всем находящимся имуществом. Отличное расположение комплекса, где также можно организовать спортивный  клуб либо замечательный спа салон.",
    "price": "12000000",
    "address": "Набережные Челны",
    "header": "Банный комплекс \"Водопад\" 617 кв.м",
    "contact": "Ришат",
    "id": "1452198000",
    "date": "9 октября"
}