{
    "text": "Эксперт- Брокер предлагает к приобретению : Недвижимое имущество в составе: 1. Здание АЗС с 4 емкостями, 4 колонками, навесом, туалетом, забором, отстойником, назначение - сервисное, площадью 18,7 кв.м., инв. номер 26, лит. А, одноэтажное, расположенное по адресу: Рязанская обл., Сасовский р-н, 418 км автодороги Москва-Самара, кадастровый (условный) номер: 62:18:0000000:360 (62-62-11/018/2006-158); 2. Земельный участок, назначение - земли сельскохозяйственного назначения, площадью 3600 кв.м, расположенный по адресу: Рязанская обл., Сасовский р-н, 418 км автодороги Москва-Самара, кад. номер 62:18:1170301:0002.",
    "price": "1001193",
    "address": "Зубова Поляна",
    "header": "АЗС",
    "contact": "Константин",
    "id": "1505607129",
    "date": null
}