{
    "text": "Сдаётся кабинет маникюра и педикюра для работы 15 дней в месяц в графике 2/2. Кабинет чистый, новый, все оборудование новое. Свой санузел не выходя из Кабинета. Кофе-машина, чайник. Зона ожидания. Полностью оборудован: Аппарат strong. Лампа LED Лампа UV Вытяжка настольная. Все для стерилизации: Уз мойка Сухожаровый шкаф Сдаётся для работы 2/2. Чистоплотность и аккуратность обязательна. Залог за 1 месяц. Для связи - лучше Watsapp. P.s. Фото делались в спешке в процессе работы.",
    "price": "13000",
    "address": "Москва",
    "header": "Кабинет маникюра и педикюра, Аренда 2/2",
    "contact": null,
    "id": "1518848073",
    "date": null
}