{
    "text": "В связи с переездом в другую страну , Продаётся готовый бизнес .Парикмахерская, расположенная  в густонаселенном жилом районе на первой линии.  Парикмахерская работает пять лет, и за это время успела наработать огромную клиентскую базу.Предоставляется широкий спектр услуг , нет текучки  кадров. Помещение-100 кв2 Арендная ставка 100 тыс рублей, из них 30 кВ м сдано в субаренду под ,, Дом быта\" за 35 тыс рублей, остаток аренды составляет 70 тыс руб. Оборот парикмахерской в месяц - 300 тыс руб, а чистый доход составляет от 80 до 100 тысяч. Парикмахерская: Ресепшн -зона администратора ,зал парикмахерских услуг,, комната для персонала,кабинет педикюра и маникюра,кабинет косметолога, подсобное помещение, Парикмахерская - укомплектована всем необходимым оборудованием, три кресла , мойка стол маникюрный на два мастера, кресло косметологическое на механизме, три зеркала и ресепшн. В смене два мастера стилиста и два мастера маникюр -педикюр . один косметолог, лешмейкер и администратор .Все работают давно и имеют постоянных клиентов. Имеется своя страничка в Инстаграмм Реклама в Яндексе и Гугле.Бизнес продаётся через переуступку прав аренды .",
    "price": "1300000",
    "address": "Котельники",
    "header": "Продается Парикмахерская",
    "contact": null,
    "id": "1552989986",
    "date": null
}