{
    "text": "Продается прибыльная и рабочая сеть ресторанов \"Чилим\" Соборная ,Чилим \"Московский\" ,Бар музей \"Сикера\" , расположенные в отдельно стоящих зданиях, в лучших локациях города . Рестораны полностью укомплектован всем оборудованием (список по запросу). Аренда везде  до 2022г. Получена алкогольная лицензия до 09.2019 года. Правовая форма – ООО с 1 учредителем. Собственный СОФТ управления рестораном 1 200 000(стоимость) Депозиты аренды – 350 000 руб. Товарных остатков более чем 500 000. Маркетинг план на 1 год. Мобильное приложение . Есть полность укоплектованный пакет на франшизу. •\tпопулярный бренд; •\tуспешная бизнес-модель; •\tстандарты обучения •\tперечень подрядчиков и изготовителей деталей интерьера и оборудования; •\tрецептуры и технологии приготовления блюд; •\tперечень рекомендованных поставщиков; •\tвысочайшие стандарты обслуживания; •\tинструкцию по открытию и управлению рестораном; •\tспецификации оборудования; •\tуникальные маркетинговые и рекламные решения. •\tАттестация ключевого персонала; Новому владельцу будут переданы все активы и оказана консультационная поддержка в течении двух месяцев после продажи!",
    "price": "1",
    "address": "Рязань",
    "header": "Прибыльный сетевой бизнес",
    "contact": null,
    "id": "1568420792",
    "date": "8 октября"
}