{
    "text": "Продаётся Студия красоты и Загара. Срок существования бизнеса 15 лет. Количество работников: 7 Салон находится в ЖК Зеон, напротив Баргузин. Хорошая проходимость, за это время наработана большая клиентская база, много постоянных клиентов. Аренда 50000 р/мес. Среднемесячные обороты в сезон 170000-230000 р/ мес. Среднемесячные обороты в не сезон (август, сентябрь, январь) 80000-120000 р/мес. Подсчёт прибыли без учета процедуры фиш-пилинг, если запускать данную процедуру плюсом к доходу от 100000 -250000 р/мес. Услуги Салона: - 3 кабинки солярия; - Шугаринг; - Наращивание ресниц; - Маникюр; - Лечение волос; - Оформление бровей. В студии стоят 3 дорогих турбосолярия, производства Италия и Германия, 2 вертикальных, 1 горизонтальный - единственный такой в городе. Все документы имеются. Во всех кабинках была произведена замена ламп. В студии есть комната для Фиш-пилинга ног, поставили все необходимое новое оборудование. Такая услуга единственная во всем городе, ближайший город с такой услугой это Братск. Если дать правильное направление то будет идти очень хороший доход. Мы данную тему не особо развивали, но люди интересовались каждый день! У данного бизнеса нет понятия сезонности, клиенты на процедуру будут всегда. Все мастера остаются, работают на аренде и на процентах. возле студии весит Вывеска. Места в студии полностью оборудованны всем необходимым. Студия вложений не требует, заходи и работай.",
    "price": "650000",
    "address": "Иркутск",
    "header": "Салон красоты",
    "contact": null,
    "id": "1594914225",
    "date": null
}