{
    "text": "Продам недействующий убойный пункт в с. Воеводское Целинного района, в 45 км. от Бийска. Земельный участок площадью 2,38 га На участке расположены 3 здания: площадью 465 м², 253 м² и 49 м². Есть вода и электричество. Земля и здания в собственности. Возможна продажа вместе с ООО (зарегистрировано более 10 лет). Торг уместен.",
    "price": "1350000",
    "address": "Целинное",
    "header": "Бойня крс (убойный цех, скотобойня)",
    "contact": "Григорий (собственник)",
    "id": "1628035767",
    "date": null
}