{
    "text": "Отлаженное, стабильно работающее предприятие. Производство шлакоблоков, брусчатки, тротуарной плитки, ремонт и изготовление рукавов высокого давления (РВД), штат рабочего персонала, техника ( кара, вилочный погрузчик, мазда титан самосвал), мех-цех со станками, 2 токарных(к-62, м-63), 2 фрезерных( вертикальный и горизонтальный), долбежный , 3 сверлильных. Кузня с молотом и станок Ажур универсал,полимерная покраска  с печкой и станком для покраски (самая большая камера в городе), столярка. 1000 м2 отапливаемого помещения, общая площадь 4000 м2, все это в собственности. Все вопросы по указанному номеру телефона.",
    "price": "15",
    "address": "Ачинск",
    "header": "Готовый бизнес с территорией в собственности",
    "contact": null,
    "id": "1656381727",
    "date": "8 октября"
}