{
    "text": "Продается  кафе \"Берендей\". Расположено на солотчинском повороте а/д \"Рязань-Спас-Клепики\": Здание кафе 350 кв.м. полностью оборудовано для организации общественного питания, проведения коллективных мероприятий. Коммуникации: газопровод, котельная, скважина, электричество, канализация. Благоустроенный земельный участок 35 соток, возможно расширение.",
    "price": "16500000",
    "address": "Рязань",
    "header": "Кафе берендей",
    "contact": null,
    "id": "1657361552",
    "date": "8 октября"
}