{
    "text": "Продается от собственника  Иглинский район, с. Иглино, по ул. Горького, общей площадью 165,5 кв.м, автомастерская (помещение под автосервис), три бокса, электроотопление, напряжение 380 вольт, вода центральная, высота помещения 4 метра. Имеется оборудование шиномонтажное и подъемник 3,5 тонны. Территория асфальтированная, отдельно вагончик шиномонтажа, забор по периметру. \"Красная линия\" с высоким трафиком с постоянными клиентами.все в собственности.",
    "price": "5000000",
    "address": "Иглино",
    "header": "Автосервисное обслуживание",
    "contact": null,
    "id": "1718932860",
    "date": "9 октября"
}