{
    "text": "Продаю от собственника действующую АЗС с земельным участком 1га(собственность)..31й километр трассы Великий Новгород -Луга(Батецкий район)...Собственность..Две Наровские (модель  5112)2х шланговые  колонки  на 2 ручья с пистолетами,система управления -ТОПАЗ АЗС,контроллер- ТОПАЗ 103 МК1, 2 здания(одно из них здание магазина-ларька)2 подстанции мощностью на 600квт и 100квт,2 ёмкости -цистерны по 50 т вместимостью каждая, новая система электроосвещения с громоотводами (12 столбов и 15 фонарей),септик,отсыпано 2000кв.м. под асфальтом для строительства мотеля,пакет документов,хорошая проходимость...6 млн. рубл.В связи с вводом в эксплуатацию и открытием Деревяницкого моста через р.Волхов автотрафик возрастает  на 30-50%.Летняя скидка на стоимость ! Спешите!Ниже нигде не найдёте!Пробка в Трегубово.В Спб ездят через Лугу!",
    "price": "6000000",
    "address": "Великий Новгород",
    "header": "Продам АЗС",
    "contact": "Андрей",
    "id": "334192186",
    "date": null
}