{
    "text": "Предлагается действующий и прибыльный бизнес (Свадебный салон), оформленный в современном и модном дизайне. Преимущества: - Окупаемость от  5 месяцев. - Налажены регулярные поставки платьев и аксессуаров (поставщиков отдам). - Наработана база клиентов. - Раскрученный сайт - Настроена контекстная реклама (Яндекс, Гугл) - Имеется видеонаблюдение, wi-fi. - Кондиционер В стоимость входит: - наработанное место, - оборудование, - фурнитура (фаты, аксессуары, шубки, чехлы, подъюбники и т.д.) - грамотно оформленная фото зона и примерочная - реальному покупателю приятный сюрприз Рассматриваю варианты продажи салона, как с платьями, так и без. Все платья из последней коллекции 2017 и 2018 года.",
    "price": "900000",
    "address": "Воронеж",
    "header": "Продается действующий Свадебный салон",
    "contact": null,
    "id": "583163671",
    "date": "9 октября"
}