{
    "text": "Готовый бизнес с арендатором (автосервис)!!! В настоящее время сдается за 45000 руб/мес. (долгосрочная аренда). Охраняемая территория, видеонаблюдение. Наружные стены: термошуба (7 слоев: фасадный утеплитель 10 мм Baswool, клей, сетка, клей, декоративная штукатурка \"короед\", грунтовка, фасадная краска 2 цвета). 1 этаж: 48 м2 (6х8 метров), высокие потолки, перекрытия усилены цельносварной металлической фермой, перегородка между боксами снесена - единое пространство 2 смотровые ямы 2 этаж: 48 м2, 3 кабинета + холл. Пластиковые стеклопакеты. Отделка. 6х8 м2. цоколь: 2 смотровые ямы + 2 подвальных помещения (всего около 6 м2) 25 кВт, 380 Капитальное здание расположено в ГСК. Собственник. Членская книжка гаражного кооператива. Разумный торг приветствуется!) Возможен обмен на двух- или трехкомнатную квартиру в Сочи (Лазаревское) удаленностью от моря не более 300 метров или коммерческую недвижимость в Лазаревке. Продаю в связи с переездом в Сочи. Рассмотрю варианты.",
    "price": "3999000",
    "address": "Домодедово",
    "header": "Автосервис сто с арендатором",
    "contact": null,
    "id": "926682474",
    "date": null
}