{
    "text": "Продам готовый действующий бизнес в сфере фотоуслуг(перечень оказываемых услуг большой) . Фото салон находится в центре города в начале проспекта Мира, действует 11 лет. Кроме фотоуслуг оказываются услуги полиграфии и изготовление сувенирной продукции, продажа и изготовление постеров,  много постоянных клиентов. Цена договорная. Звоните, отвечу по телефону на все вопросы.",
    "price": null,
    "address": "Кострома",
    "header": "Фотосалон",
    "contact": "Анна",
    "id": "950505934",
    "date": null
}