{
    "text": "Готовый бизнес: интернет-портал по теме «Развлечения (прогулки и рестораны) Москва» УТП – идейные прогулки с посещением ресторана-рекламодателя Концепция бизнеса – рекламная площадка с уникальным контентом в формате «продакт плейсмент» для размещения кафе, ресторанов и баров на коммерческой основе. 1)  Старт бизнеса – август 2013 год, 2) Накоплено около 200 маршрутов. 3) Топовые позиции по выдаче в Google и Яндекс - 1 страница по ключевым запросам «Куда пойти с девушкой», «Куда пойти с друзьями», «Куда пойти с детьми» и аналогичным. 4) Доход сайта обеспечивается за счет: - рекламы рестораторов в прогулках - баннерной рекламы, -  платного размещения на платформе мероприятий, афиш и меню, - платных публикаций в соц.сетях, - рекламных блоков Яндекса. 5) Seo-продвижение позволяет обеспечивать до 60 тыс.уникальных посетителей и до 120 тыс.просмотров 6) Соц.сети: = ВК - 10.500 подписчиков, = Фейсбук - 11.000 подписчиков, = Инстаграм – 7.200 подписчиков. 7) Расходы на ведение сайта: 15.000-17.000 руб./мес. Причины продажи: сайт делался на продажу. Полное переоформление, 1 владелец. Цена продажи: 600.000 руб.",
    "price": "475000",
    "address": "Москва",
    "header": "Интернет-портал по развлечениям в Москве",
    "contact": "Олег",
    "id": "989168817",
    "date": null
}